joka/metadata.py
joka/joplan/__init__.py
joka/joplan/cli.py
joka/joview/__init__.py
joka/joview/cli.py
joka-0.0.1.dist-info/METADATA
joka-0.0.1.dist-info/WHEEL
joka-0.0.1.dist-info/entry_points.txt
joka-0.0.1.dist-info/RECORD
